{"language":"grc","conditions":{"v":{"name":"Verb","isDictionaryForm":true},"n":{"name":"Noun","isDictionaryForm":true},"adj":{"name":"Adjective","isDictionaryForm":true}},"transforms":{"2nd person singular present active indicative":{"name":"2nd person singular present active indicative","description":"","rules":[{"type":"suffix","fromSuffix":"εις","toSuffix":"ω","conditionsIn":[],"conditionsOut":["v"]},{"type":"suffix","fromSuffix":"εις","toSuffix":"εω","conditionsIn":[],"conditionsOut":["v"]}]},"3rd person singular present active indicative":{"name":"3rd person singular present active indicative","description":"","rules":[{"type":"suffix","fromSuffix":"ει","toSuffix":"ω","conditionsIn":[],"conditionsOut":["v"]},{"type":"suffix","fromSuffix":"ει","toSuffix":"εω","conditionsIn":[],"conditionsOut":["v"]}]},"1st person plural present active indicative":{"name":"1st person plural present active indicative","description":"","rules":[{"type":"suffix","fromSuffix":"ομεν","toSuffix":"ω","conditionsIn":[],"conditionsOut":["v"]}]},"2nd person plural present active indicative":{"name":"2nd person plural present active indicative","description":"","rules":[{"type":"suffix","fromSuffix":"ετε","toSuffix":"ω","conditionsIn":[],"conditionsOut":["v"]}]},"3rd person plural present active indicative":{"name":"3rd person plural present active indicative","description":"","rules":[{"type":"suffix","fromSuffix":"ουσι","toSuffix":"ω","conditionsIn":[],"conditionsOut":["v"]},{"type":"suffix","fromSuffix":"ουσιν","toSuffix":"ω","conditionsIn":[],"conditionsOut":["v"]}]},"2nd person singular present middle indicative":{"name":"2nd person singular present middle indicative","description":"","rules":[{"type":"suffix","fromSuffix":"ῃ","toSuffix":"ομαι","conditionsIn":[],"conditionsOut":["v"]},{"type":"suffix","fromSuffix":"ει","toSuffix":"ομαι","conditionsIn":[],"conditionsOut":["v"]}]},"3rd person singular present middle indicative":{"name":"3rd person singular present middle indicative","description":"","rules":[{"type":"suffix","fromSuffix":"εται","toSuffix":"ομαι","conditionsIn":[],"conditionsOut":["v"]}]},"1st person plural present middle indicative":{"name":"1st person plural present middle indicative","description":"","rules":[{"type":"suffix","fromSuffix":"ομεθα","toSuffix":"ομαι","conditionsIn":[],"conditionsOut":["v"]}]},"2nd person plural present middle indicative":{"name":"2nd person plural present middle indicative","description":"","rules":[{"type":"suffix","fromSuffix":"εσθε","toSuffix":"ομαι","conditionsIn":[],"conditionsOut":["v"]}]},"3rd person plural present middle indicative":{"name":"3rd person plural present middle indicative","description":"","rules":[{"type":"suffix","fromSuffix":"ονται","toSuffix":"ομαι","conditionsIn":[],"conditionsOut":["v"]}]},"genitive singular":{"name":"genitive singular","description":"","rules":[{"type":"suffix","fromSuffix":"ου","toSuffix":"ος","conditionsIn":[],"conditionsOut":["n"]},{"type":"suffix","fromSuffix":"ας","toSuffix":"α","conditionsIn":[],"conditionsOut":["n"]},{"type":"suffix","fromSuffix":"ου","toSuffix":"ας","conditionsIn":[],"conditionsOut":["n"]},{"type":"suffix","fromSuffix":"ου","toSuffix":"ον","conditionsIn":[],"conditionsOut":["n"]},{"type":"suffix","fromSuffix":"ης","toSuffix":"η","conditionsIn":[],"conditionsOut":["n"]}]},"dative singular":{"name":"dative singular","description":"","rules":[{"type":"suffix","fromSuffix":"ω","toSuffix":"ος","conditionsIn":[],"conditionsOut":["n"]},{"type":"suffix","fromSuffix":"α","toSuffix":"ας","conditionsIn":[],"conditionsOut":["n"]},{"type":"suffix","fromSuffix":"ω","toSuffix":"ον","conditionsIn":[],"conditionsOut":["n"]}]},"accusative singular":{"name":"accusative singular","description":"","rules":[{"type":"suffix","fromSuffix":"ον","toSuffix":"ος","conditionsIn":[],"conditionsOut":["n"]},{"type":"suffix","fromSuffix":"αν","toSuffix":"α","conditionsIn":[],"conditionsOut":["n"]},{"type":"suffix","fromSuffix":"αν","toSuffix":"ας","conditionsIn":[],"conditionsOut":["n"]},{"type":"suffix","fromSuffix":"ην","toSuffix":"η","conditionsIn":[],"conditionsOut":["n"]}]},"vocative singular":{"name":"vocative singular","description":"","rules":[{"type":"suffix","fromSuffix":"ε","toSuffix":"ος","conditionsIn":[],"conditionsOut":["n"]},{"type":"suffix","fromSuffix":"α","toSuffix":"ας","conditionsIn":[],"conditionsOut":["n"]},{"type":"suffix","fromSuffix":"η","toSuffix":"η","conditionsIn":[],"conditionsOut":["n"]}]},"nominative plural":{"name":"nominative plural","description":"","rules":[{"type":"suffix","fromSuffix":"οι","toSuffix":"ος","conditionsIn":[],"conditionsOut":["n"]},{"type":"suffix","fromSuffix":"αι","toSuffix":"α","conditionsIn":[],"conditionsOut":["n"]},{"type":"suffix","fromSuffix":"αι","toSuffix":"ας","conditionsIn":[],"conditionsOut":["n"]},{"type":"suffix","fromSuffix":"α","toSuffix":"ον","conditionsIn":[],"conditionsOut":["n"]},{"type":"suffix","fromSuffix":"αι","toSuffix":"η","conditionsIn":[],"conditionsOut":["n"]}]},"genitive plural":{"name":"genitive plural","description":"","rules":[{"type":"suffix","fromSuffix":"ων","toSuffix":"ος","conditionsIn":[],"conditionsOut":["n"]},{"type":"suffix","fromSuffix":"ων","toSuffix":"α","conditionsIn":[],"conditionsOut":["n"]},{"type":"suffix","fromSuffix":"ων","toSuffix":"ας","conditionsIn":[],"conditionsOut":["n"]},{"type":"suffix","fromSuffix":"ων","toSuffix":"ον","conditionsIn":[],"conditionsOut":["n"]},{"type":"suffix","fromSuffix":"ων","toSuffix":"η","conditionsIn":[],"conditionsOut":["n"]}]},"dative plural":{"name":"dative plural","description":"","rules":[{"type":"suffix","fromSuffix":"οις","toSuffix":"ος","conditionsIn":[],"conditionsOut":["n"]},{"type":"suffix","fromSuffix":"αις","toSuffix":"α","conditionsIn":[],"conditionsOut":["n"]},{"type":"suffix","fromSuffix":"αις","toSuffix":"ας","conditionsIn":[],"conditionsOut":["n"]},{"type":"suffix","fromSuffix":"οις","toSuffix":"ον","conditionsIn":[],"conditionsOut":["n"]},{"type":"suffix","fromSuffix":"αις","toSuffix":"η","conditionsIn":[],"conditionsOut":["n"]}]},"accusative plural":{"name":"accusative plural","description":"","rules":[{"type":"suffix","fromSuffix":"ους","toSuffix":"ος","conditionsIn":[],"conditionsOut":["n"]},{"type":"suffix","fromSuffix":"ας","toSuffix":"α","conditionsIn":[],"conditionsOut":["n"]},{"type":"suffix","fromSuffix":"α","toSuffix":"ον","conditionsIn":[],"conditionsOut":["n"]},{"type":"suffix","fromSuffix":"ας","toSuffix":"η","conditionsIn":[],"conditionsOut":["n"]}]},"vocative plural":{"name":"vocative plural","description":"","rules":[{"type":"suffix","fromSuffix":"οι","toSuffix":"ος","conditionsIn":[],"conditionsOut":["n"]},{"type":"suffix","fromSuffix":"αι","toSuffix":"α","conditionsIn":[],"conditionsOut":["n"]},{"type":"suffix","fromSuffix":"αι","toSuffix":"ας","conditionsIn":[],"conditionsOut":["n"]},{"type":"suffix","fromSuffix":"α","toSuffix":"ον","conditionsIn":[],"conditionsOut":["n"]},{"type":"suffix","fromSuffix":"αι","toSuffix":"η","conditionsIn":[],"conditionsOut":["n"]}]},"accusative singular masculine":{"name":"accusative singular masculine","description":"","rules":[{"type":"suffix","fromSuffix":"ον","toSuffix":"ος","conditionsIn":[],"conditionsOut":["adj"]}]},"nominalization":{"name":"nominalization","description":"","rules":[{"type":"suffix","fromSuffix":"ος","toSuffix":"εω","conditionsIn":[],"conditionsOut":["v"]}]}}}